python_wizard/__init__.py
python_wizard/cant_use_pw.py
python_wizard/fix_bug_pw.py
python_wizard/pw_dict.py
python_wizard/pw_list.py
python_wizard/sandbox1_pw.py
python_wizard/utils.py
python_wizard/utils_pw.py
python_wizard-0.1.5.dist-info/METADATA
python_wizard-0.1.5.dist-info/WHEEL
python_wizard-0.1.5.dist-info/top_level.txt
python_wizard-0.1.5.dist-info/RECORD
