Metadata-Version: 2.1
Name: python_wizard
Version: 0.1.5
Summary: Package that would help shorten your python code providing additional functions ready to use
Home-page: https://github.com/DearNorathee/python_wizard
Author: Dear Norathee
Author-email: noratee5@hotmail.com
License: MIT
